setup.py
dedent/__init__.py
dedent/__main__.py
dedent.egg-info/PKG-INFO
dedent.egg-info/SOURCES.txt
dedent.egg-info/dependency_links.txt
dedent.egg-info/not-zip-safe
dedent.egg-info/requires.txt
dedent.egg-info/top_level.txt